ptvis/__init__.py
ptvis/_typing.py
ptvis/_version.py
ptvis/color.py
ptvis/components.py
ptvis/layouts.py
ptvis/py.typed
ptvis/utils.py
ptvis/core/__init__.py
ptvis/core/attaching.py
ptvis/core/element.py
ptvis-2.1.0.dist-info/licenses/LICENSE.txt
ptvis-2.1.0.dist-info/METADATA
ptvis-2.1.0.dist-info/WHEEL
ptvis-2.1.0.dist-info/top_level.txt
ptvis-2.1.0.dist-info/RECORD
